draftsdownload/__init__.py
draftsdownload-2.0.0.dist-info/DESCRIPTION.rst
draftsdownload-2.0.0.dist-info/METADATA
draftsdownload-2.0.0.dist-info/RECORD
draftsdownload-2.0.0.dist-info/WHEEL
draftsdownload-2.0.0.dist-info/entry_points.txt
draftsdownload-2.0.0.dist-info/metadata.json
draftsdownload-2.0.0.dist-info/top_level.txt
